{
  "frames": [
    {
      "name": "Warrior",
      "variants": []
    },
    {
      "name": "Warrior IV",
      "variants": []
    },
    {
      "name": "Jackal",
      "variants": []
    },
    {
      "name": "Spartan",
      "variants": []
    },
    {
      "name": "Gladiator",
      "variants": []
    },
    {
      "name": "Pitbull",
      "variants": []
    },
    {
      "name": "Mustang",
      "variants": []
    },
    {
      "name": "Greyhound",
      "variants": []
    },
    {
      "name": "Harrier",
      "variants": []
    },
    {
      "name": "Skirmisher",
      "variants": []
    },
    {
      "name": "Shinobi",
      "variants": []
    },
    {
      "name": "Crusader IV",
      "variants": []
    },
    {
      "name": "Argos",
      "variants": []
    },
    {
      "name": "Cataphract",
      "variants": []
    },
    {
      "name": "Uhlan",
      "variants": []
    },
    {
      "name": "Coyote",
      "variants": []
    },
    {
      "name": "Red Bull Mk2",
      "variants": []
    },
    {
      "name": "Mameluk",
      "variants": []
    },
    {
      "name": "Mastiff",
      "variants": []
    },
    {
      "name": "Hoplite",
      "variants": []
    },
    {
      "name": "Black Wind",
      "variants": []
    }
  ]
}
